better_pywhois/__init__.py
better_pywhois/protocol.py
better_pywhois/utils.py
better_pywhois-0.0.1.dist-info/DESCRIPTION.rst
better_pywhois-0.0.1.dist-info/METADATA
better_pywhois-0.0.1.dist-info/RECORD
better_pywhois-0.0.1.dist-info/WHEEL
better_pywhois-0.0.1.dist-info/metadata.json
better_pywhois-0.0.1.dist-info/top_level.txt
