Metadata-Version: 2.0
Name: better-pywhois
Version: 0.0.1
Summary: a WHOIS library for Python
Home-page: https://github.com/bitcynth/better-pywhois
Author: Cynthia Revstrom
Author-email: me@cynthia.re
License: MIT
Keywords: whois
Platform: UNKNOWN
Classifier: Programming Language :: Python :: 3
Classifier: License :: OSI Approved :: MIT License
Classifier: Operating System :: OS Independent
